speliuk/__init__.py
speliuk/correct.py
speliuk/train.py
speliuk-0.0.2.dist-info/METADATA
speliuk-0.0.2.dist-info/WHEEL
speliuk-0.0.2.dist-info/RECORD
