Metadata-Version: 2.1
Name: speliuk
Version: 0.0.2
Summary: Speliuk is a spell checker for the Ukrainian language based on SymSpell and Language Models.
License: MIT
Author: Oleh Neichev
Author-email: oleg.neichev@gmail.com
Requires-Python: >=3.8,<4.0
Classifier: License :: OSI Approved :: MIT License
Classifier: Programming Language :: Python :: 3
Classifier: Programming Language :: Python :: 3.8
Classifier: Programming Language :: Python :: 3.9
Classifier: Programming Language :: Python :: 3.10
Classifier: Programming Language :: Python :: 3.11
Classifier: Programming Language :: Python :: 3.12
Requires-Dist: kenlm (==0.2.0)
Requires-Dist: spacy (>=3.7.5,<4.0.0)
Requires-Dist: spacy-transformers (>=1.3.5,<2.0.0)
Requires-Dist: symspellpy (>=6.7.7,<7.0.0)
Requires-Dist: ua-gec (>=2.1.3,<3.0.0)
